{"kk3URLID3u0lFEvpO3twNA==":"0-1-19-600x292.jpg","fbF8iP5SaR81jVtR7Akfgg==":"0-1-15-600x292.jpg","pnAGhxC7NUBk0KmU5/nD9w==":"0-1-7-600x292.jpg","HFy0/2e+r7qXN54vgjnZrQ==":"0-2-8-600x292.jpg","Aw4Byyruy8GATprVhsUFiw==":"1logo-128x128.png","5UdBKxm/+sfJyW/Ejb+deA==":"1logo-1-128x128.png","MabqQZojtMYkTDNt7vbyQw==":"0-1-20-600x292.jpg","KHjvMuGEiDuxubF2TqFDrw==":"0-1-16-600x292.jpg","wym1aItMTTVbz8GqtbucPA==":"0-1-8-600x292.jpg","QFx1kJb2hDF1QMsWt2T4wg==":"0-2-9-600x292.jpg","ad7s/ZksVJjA+uvyNoaLEA==":"0-1-21-600x292.jpg","qimc0CnlZU/UVihgOnEGqA==":"0-1-17-600x292.jpg","5Tq1AcmpdsZ+b8hUnjMgyg==":"0-1-9-600x292.jpg","JyV3mhl2Or/lWR4QZ6wL5w==":"0-2-10-600x292.jpg","ucFq7Irxyam/xbO9rVEscA==":"1logo-2-128x128.png","UpEPlu6xcST7V5XDX/ay0A==":"logo-128x128.png","M763v2Q/kTTMKM9JIPrAag==":"0-1-5-460x230.jpg","n3tv0xTJ3apgSH5EH2Xjbg==":"0-1-6-460x230.jpg","L5b1CQTIH+l8eLGjw3UEwA==":"0-1-7-460x230.jpg","7hqJtMl2G3aPuNGChHFrFQ==":"0-1-8-460x230.jpg","LXUJIGYMrjX4+U8e8N/tzA==":"0-2-3-460x230.jpg","L70igT2RQAslgAV7XY4/WA==":"1logo-3-128x128.png","4AqCrkwMweZlVbv1d9P88Q==":"1logo-4-128x128.png","ZKtHKnePnOekMdzS3lOncg==":"2-1-1-1.png","VZcr2MnPE8ZnPs+Z0FvO3w==":"2-1-3-1.jpg","XmbjThxyIuwdSGU9NoOW6A==":"2-1-2-1.png","Qfs+75TZBqirPDWjeqwDng==":"2-1-1-19-1.png","t5uraWi6sPJ2XSh4sF+UqQ==":"2-1-1-15-1.png","2dJAkhRGpMmBChaSGEF/Hg==":"2-2-4-1.jpg","v2KPPBsTJ+zeZiY6sD5WGA==":"2-3-1-1.png","aiL8SvkvBgCG02MHnWs5bA==":"20120522043857homer-simpson-1.png","WGpX4k9PepaVX8xXZxvAmw==":"familyguy-peter-griffin-72.jpg","8IbzIxI+ACoKUBDyDwAsnA==":"patrick-star-4854.jpg","w79u0zx7iFtCzXW1gqFgGQ==":"familyguy-peter-griffin-73.jpg","7Nt3UUbPyoSIchGY01bE+w==":"20120522043857homer-simpson-2.png","RrnsRmYxePJPqHpEq8nx9w==":"54.jpg","Tm7P44Zl6+jb6dHm7rpyLA==":"logo.png","UuU/oxoUZDSPoPjl8XJYJw==":"2-1-1-17-1.png","s3KMx8MlS/MS2ACE7bD81Q==":"2-1-1-14-1.png","20YypateKyZ32YHw9cOq/g==":"hs.jpg","foJ1bxAb7/7u3QidqL7RJQ==":"1logo-5-128x128.png","lgdKBwRRNGh8aOEwfok0JA==":"-7.jpg","h5ZKysslMcTD+NaRJyH2eQ==":"-8.jpg","pZ7pR0lLz2ch/yzHKI97sQ==":"-9.jpg","iUsd5jSKH3DF/L2EWpW8ig==":"1logo.png","9GA0A/z2CVe8pYmZslq2Fw==":"1logo-1.png","4pexA8r3OuGAz/HSuH+Jcw==":"1logo-2.png","ydaqCQlSwg42U11N3D0CuQ==":"1logo-3.png","R9Ew8P6Uc2Clxw9/iQvc8w==":"-10.jpg","Q/n62s8HK3/UPD/3e6T7vA==":"-11.jpg","Si7XeZ70W2jXHd1K4jIfuw==":"-6.png","vNUjPxXAWhJKzBEsXf4rYA==":"-7.png","HEjRZGutfxOEcsc/WKfKfA==":"-12.jpg","Am3a83Zq9dmoB5g+ybuGfQ==":"-13.jpg","X3fA3dyfEb9tSAlLLiIxXQ==":"-14.jpg","X/fb6hpQB9NRMoNhQV70Rw==":"-8.png","9MIEu0MJ9Qx2nO9e2HmydQ==":"-9.png","Eh7Y+QfVQyPnkYlXgC+R/w==":"-10.png","4UW6gnX6esnTKAbwpZ6sXQ==":"-11.png","h8DWFj886YqjLYgTzE0UAg==":"-15.jpg","Vxfm9Ee1SgbqAraNupWvEg==":"-12.png","LkTQoXXrBj6WojWxzMgx8A==":"-16.jpg"}